[
    {
        "title": "VallbonAR",
        "tech": "Kotlin · TypeScript · C# · Unity",
        "description": "Final year Multiplatform Development (DAM) project developed in a team. I contributed to the mobile application and the augmented reality navigation system for indoor positioning in educational environments.",
        "features": [
            "Android App using Jetpack Compose",
            "Use of Firebase for notifications",
            "Augmented Reality Navigation with Unity AR foundation",
            "ARCore Integration",
            "API backend done in Typescript using Sanity CMS"
        ],
        "github": "https://github.com/IDelgadoSancho/vallbonAR",
        "images": [
            "media/pics/vallbonAR_pic1.webp",
            "media/pics/vallbonAR_pic2.webp",
            "media/pics/vallbonAR_pic3.webp"
        ]
    },
    {
        "title": "Peer2Stream",
        "tech": "Next.js · Node.js · MongoDB",
        "description": "Final year Web Development (DAW) project developed in a team. I focused mainly on frontend development and API integration using Next.js and Node.js.",
        "features": [
            "Favorites and Notifications",
            "Routing and API consumption with Node.js",
            "Use of TMDB API",
            "Use of JWT tokens for the authentication",
            "Compatibilty with external plugins"
        ],
        "github": "https://github.com/IDelgadoSancho/peer2stream",
        "images": [
            "media/pics/peer2stream_pic1.webp",
            "media/pics/peer2stream_pic2.webp",
            "media/pics/peer2stream_pic3.webp"
        ]
    },
    {
        "title": "Laravel CRUD",
        "tech": "PHP · Laravel · MySQL · HTML · CSS/Tailwind",
        "description": "Full stack CRUD application developed with Laravel. Focused on managing structured data with clean architecture and basic authentication.",
        "features": [
            "Full CRUD system (create, read, update, delete)",
            "Blade templates for frontend rendering",
            "Form validation and error handling",
            "Database integration with MySQL/SQLite",
            "Basic authentication and user roles"
        ],
        "github": "https://github.com/IDelgadoSancho/crud_laravel",
        "images": [
            "media/pics/laravelCrud_pic1.webp",
            "media/pics/laravelCrud_pic2.webp",
            "media/pics/laravelCrud_pic3.webp"
        ]
    },
    {
        "title": "Space-Survivors",
        "tech": "C# · Unity",
        "description": "My first step in game development in Unity. A top-down Vampire Survivors like game. I used free assets from Unity Store and Itch.io",
        "features": [
            "2D movement and shooting mechanics",
            "Enemy spawning system",
            "Basic wave progression",
            "Collision and damage system",
            "Done with Android in mind, but it can be play on PC"
        ],
        "github": "https://github.com/IDelgadoSancho/Space-Survivors",
        "images": [
            "media/pics/Space-Survivors_pic1.webp",
            "media/pics/Space-Survivors_pic2.webp",
            "media/pics/Space-Survivors_pic3.webp"
        ]
    }
]